{
  "riskThresholds": {
    "block": 0.62,
    "warn": 0.32
  },
  "baseRiskScores": {
    "invalidFormat": 0.8,
    "disposableDomain": 0.7,
    "highEntropy": 0.7
  },
  "confidenceThresholds": {
    "markovFraud": 0.72,
    "markovRisk": 0.6,
    "patternRisk": 0.45
  },
  "features": {
    "enableDisposableCheck": false,
    "enablePatternCheck": true,
    "enableTLDRiskProfiling": false,
    "enableMarkovChainDetection": true
  },
  "logging": {
    "logAllValidations": true,
    "logLevel": "debug",
    "logBlocks": true
  },
  "headers": {
    "enableResponseHeaders": true,
    "enableOriginHeaders": false,
    "originUrl": ""
  },
  "actionOverride": null,
  "riskWeights": {
    "domainReputation": 0.1,
    "tldRisk": 0.05
  },
  "patternThresholds": {
    "sequential": 0.6,
    "dated": 0.6,
    "plusAddressing": 0.55,
    "keyboardWalk": 0.8,
    "gibberish": 0.8
  },
  "rateLimiting": {
    "enabled": false,
    "maxValidationsPerMinute": 60,
    "maxValidationsPerHour": 1000
  },
  "admin": {
    "enabled": false
  },
  "markov": {
    "adaptationRate": 0.5,
    "minTrainingExamples": 100,
    "retrainIntervalDays": 7
  },
  "adjustments": {
    "professionalEmailFactor": 0.5,
    "professionalDomainFactor": 0.5,
    "professionalAbnormalityFactor": 0.6
  },
  "ensemble": {
    "boostMultiplier": 0.25,
    "maxBoost": 0.3,
    "tldAgreementThreshold": 0.5
  },
  "ood": {
    "maxRisk": 0.6,
    "warnZoneMin": 0.3
  },
  "calibration": null
}
